[
    {
        "id":1,
        "firstName":"David",
        "LastName":"Harris",
        "mail":"Davidharris@gmail.com",
        "password":"David",
        "image":"https://images.unsplash.com/photo-1522075469751-3a6694fb2f61?ixlib=rb-4.0.3&ixid=MnwxMjA3fDB8MHxwaG90by1wYWdlfHx8fGVufDB8fHx8&auto=format&fit=crop&w=2960&q=80"
    },
    {
        "id":2,
        "firstName":"leo",
        "LastName":"messi",
        "mail":"Leomessi@gmail.com",
        "password":"leo",
        "image":"https://images.unsplash.com/photo-1521132293557-5b908a59d1e1?ixlib=rb-4.0.3&ixid=MnwxMjA3fDB8MHxwaG90by1wYWdlfHx8fGVufDB8fHx8&auto=format&fit=crop&w=1674&q=80"
    },
    {
        "id":3,
        "firstName":"Rebecca",
        "LastName":"Ed",
        "mail":"Rebecca@gmail.com",
        "password":"Rebecca",
        "image":"https://images.unsplash.com/photo-1573496799515-eebbb63814f2?ixlib=rb-4.0.3&ixid=MnwxMjA3fDB8MHxwaG90by1wYWdlfHx8fGVufDB8fHx8&auto=format&fit=crop&w=1769&q=80"
    },
    {
        "id":4,
        "firstName":"Robert",
        "LastName":"Payet",
        "mail":"Robert@gmail.com",
        "password":"Robert",
        "image":"https://images.unsplash.com/photo-1525357816819-392d2380d821?ixlib=rb-4.0.3&ixid=MnwxMjA3fDB8MHxwaG90by1wYWdlfHx8fGVufDB8fHx8&auto=format&fit=crop&w=1674&q=80"
    },
    {
        "id":5,
        "firstName":"Shy",
        "LastName":"Cohen",
        "mail":"ShyCohen@gmail.com",
        "password":"Shy",
        "image":"https://images.unsplash.com/photo-1607990281513-2c110a25bd8c?ixlib=rb-4.0.3&ixid=MnwxMjA3fDB8MHxwaG90by1wYWdlfHx8fGVufDB8fHx8&auto=format&fit=crop&w=1268&q=80"
    }
]